README.txt
setup.cfg
setup.py
bin/bson2json.py
bson_lazy/__init__.py
bson_lazy.egg-info/PKG-INFO
bson_lazy.egg-info/SOURCES.txt
bson_lazy.egg-info/dependency_links.txt
bson_lazy.egg-info/requires.txt
bson_lazy.egg-info/top_level.txt