Metadata-Version: 1.0
Name: bson-lazy
Version: 0.2.3
Summary: A lazy BSON file loader
Home-page: https://github.com/ShinNoNoir/bson_lazy
Author: Raynor Vliegendhart, Rick van Hattem
Author-email: ShinNoNoir@gmail.com, Rick.van.Hattem@Fawo.nl
License: LICENSE.txt
Keywords: BSON lazy
Platform: Any
